{"data_wygenerowania":"2022-02-28 16:33:02","komunikaty":[{"tytul":"15:46 Awaryjna zmiana trasy linii 106 i 111","tresc":"<p>W zwi\u0105zku z zablokowaniem mostu Popielnego na ul. Toru\u0144skiej, linie 106 i 111 kursuj\u0105 w obydwu kierunkach przez Podwale Przedmiejskie z pomini\u0119ciem ulic Toru\u0144skiej i \u0141\u0105kowej.<\/p>","url":"https:\/\/ztm.gda.pl\/komunikaty\/15-46-awaryjna-zmiana-trasy-linii-106-i-111,a,8018","data_rozpoczecia":"2022-02-28 16:14:31","data_zakonczenia":"9999-12-31 23:59:59"}]}